Workbook

Sheet Resumen
A1: Memoria de cálculo — Sistema de antenas y red para la aldea Babilonia (Chisec, Alta Verapaz)
A2: Universidad del Istmo · Antenas y Propagación 2026 · Modalidad A (simulación) · Equipo: Kevin Gabriel González Donis, Maximiliano González De León, Diego Andre Cuellar Butcher
A4: Indicador | B4: Valor | C4: Nota
A5: Casas / puntos de servicio de diseño | B5: =COUNT(Enlace_por_casa!$A$5:$A$113) -> 109 | C5: Datos de entrada: hoja Enlace_por_casa
A6: Población estimada (95 viviendas × 4.0 hab.) | B6: =95*4 -> 380 | C6: Supuesto D03
A7: Altura de la torre (m) | B7: =Supuestos!$C$7 -> 30 | C7: D07
A8: Distancia máxima a la torre (m) | B8: =MAX(Enlace_por_casa!$C$5:$C$113) -> 420.5
A9: Casas con enlace útil en bajada (margen ≥ 10 dB) | B9: =COUNTIF(Enlace_por_casa!$X$5:$X$113,"<>ninguno") -> 109 | C9: Meta: ≥ 95 % (≥ 104)
A10: Casas con enlace útil en subida | B10: =COUNTIF(Enlace_por_casa!$Z$5:$Z$113,">0") -> 109
A11: Margen mínimo de bajada sobre BPSK (dB) | B11: =MIN(Enlace_por_casa!$T$5:$T$113) -> 16.40178
A12: Margen mínimo de subida sobre BPSK (dB) | B12: =MIN(Enlace_por_casa!$U$5:$U$113) -> 13.40178 | C12: Casa 26 (41 dB de follaje)
A13: Margen mediano de bajada (dB) | B13: =MEDIAN(Enlace_por_casa!$T$5:$T$113) -> 45.146806
A14: Pérdida de follaje máxima (dB) | B14: =MAX(Enlace_por_casa!$R$5:$R$113) -> 41.214286 | C14: Weissberger a 5.8 GHz
A15: Utilización de aire máx. en bajada (año 3) | B15: =MAX(Capacidad!D5:D7) -> 0.4835503 | C15: Menor a 100 % = cabe
A16: Uso del backhaul Starlink en bajada (año 3) | B16: =Capacidad!C26 -> 0.67586207 | C16: Pico agregado vs 145 Mbps
A17: Potencia continua de la torre (W) | B17: =Energia!$D$9 -> 157.85
A18: Paneles / baterías | B18: =Energia!$D$20&" × 550 W / "&Energia!$D$15&" × 5.12 kWh" -> 3 × 550 W / 2 × 5.12 kWh | C18: Autonomía ≈ 2.4 días
A19: CAPEX total de diseño (Q) | B19: =BOM_CAPEX!$H$33 -> 396925.25 | C19: BOM_CAPEX
A20: CAPEX por hogar (Q) | B20: =BOM_CAPEX!$H$36 -> 4050.2577
A21: OPEX mensual año 3 (Q) | B21: =OPEX_Tarifa!C18 -> 8532.8081
A22: OPEX por hogar por mes, año 3 (Q) | B22: =OPEX_Tarifa!C20 -> 87.06947
A23: Tarifa de equilibrio por hogar y mes (Q) | B23: =OPEX_Tarifa!C22 -> 154.57376 | C23: OPEX + CAPEX a 5 años
A25: Contenido del libro
A26: Supuestos | B26: Todos los parámetros de entrada (azules) con su fuente
A27: MCS | B27: Tabla de modulaciones del radio y tasas PHY
A28: Enlace_por_casa | B28: Presupuesto de enlace de las 109 casas, con fórmulas
A29: Capacidad | B29: Utilización por sector, crecimiento y backhaul
A30: Interferencia | B30: Plan de frecuencias y C/I entre sectores
A31: Sensibilidad | B31: Escenarios de torre, copa, desvanecimiento y montaje
A32: Energia | B32: Dimensionamiento solar y baterías
A33: BOM_CAPEX | B33: Lista de materiales y CAPEX en Q
A34: OPEX_Tarifa | B34: OPEX, costo por hogar y tarifa
A35: Legal | B35: Marco regulatorio (SIT)
A36: Fuentes | B36: Trazabilidad de datos

Sheet Supuestos
A1: Supuestos y parámetros de diseño
A2: Azul = dato de entrada (cámbielo y todo el libro se recalcula). Negro = fórmula. Amarillo = supuesto clave.
A4: Parámetro | C4: Valor | D4: Unidad | E4: Fuente / nota
A5: Frecuencia de diseño | C5: 5.8 | D5: GHz | E5: Canal central de la banda 5725–5850 MHz (F28)
A6: Longitud de onda | C6: =299792458/(C5*1000000000) -> 0.051688355 | D6: m | E6: c / f
A7: Altura de la torre | C7: 30 | D7: m | E7: Decisión D07 (análisis de follaje, FUENTES F17)
A8: Elevación del terreno en la torre | C8: 206 | D8: m s. n. m. | E8: Google Earth (F12)
A9: Altura del CPE sobre el terreno (mástil) | C9: 6 | D9: m | E9: Supuesto de diseño (mástil sobre techo)
A10: Ganancia del CPE LiteBeam 5AC Gen2 | C10: 23 | D10: dBi | E10: Ficha F27
A11: Pérdida de jumpers/conectores en el AP | C11: 0.5 | D11: dB | E11: Supuesto
A12: Pérdida por desalineación del CPE | C12: 1 | D12: dB | E12: Supuesto
A13: Pérdida por lluvia (trayecto ≤ 0.42 km) | C13: 0.3 | D13: dB | E13: UIT-R P.838-3, valor aproximado (por verificar)
A14: Penalización de sensibilidad por canal de 20 MHz | C14: 3 | D14: dB | E14: Supuesto conservador: la ficha F24 da la sensibilidad en otro ancho de canal
A15: Tx del CPE por debajo del AP | C15: 3 | D15: dB | E15: 25 dBm (CPE) frente a 28 dBm (AP)
A16: Margen de diseño exigido (M_req) | C16: 10 | D16: dB | E16: Criterio del proyecto (FICHA §9)
A17: Eficiencia MAC (TDD) | C17: 0.65 | E17: Supuesto
A18: Fracción de la trama para bajada | C18: 0.75 | E18: Supuesto
A19: Ganancia sectorial AM-5G16-120 | C19: 15.5 | D19: dBi | E19: Ficha F25: 15–16 dBi (valor medio)
A20: Ancho de haz horizontal a 6 dB | C20: 137 | D20: ° | E20: Ficha F25
A21: Inclinación de fábrica (elevación) | C21: 4 | D21: ° | E21: Ficha F25
A22: Inclinación mecánica adicional | C22: 0 | D22: ° | E22: Decisión D16
A23: Largo físico de la antena sectorial | C23: 0.367 | D23: m | E23: Ficha F25 (367 mm)
A24: Tope de atenuación azimutal (F/B y laterales) | C24: 25 | D24: dB | E24: SUPUESTO: la ficha no da F/B
A25: Piso de atenuación en elevación | C25: 25 | D25: dB | E25: SUPUESTO
A26: Acimut del eje S1 / S2 / S3 | C26: 150 | D26: ° | E26: Sector S1: 90–210°
C27: 270 | D27: ° | E27: Sector S2: 210–330°
C28: 30 | D28: ° | E28: Sector S3: 330–90°
A29: Adopción de diseño (año 3) | C29: 0.9 | E29: D04
A30: Demanda media por suscriptor en hora pico (bajada) | C30: 1 | D30: Mbps | E30: 4 Mbps por usuario activo × 25 % de simultaneidad
A31: Demanda media por suscriptor en hora pico (subida) | C31: 0.125 | D31: Mbps | E31: 0.5 Mbps × 25 %
A32: Tipo de cambio | C32: 7.6445 | D32: GTQ/USD | E32: F22 (26-oct-2026)

Sheet MCS
A1: Tabla de modulaciones del Rocket Prism 5AC Gen2
A2: Fuente F24 (netxl). La sensibilidad es la de la ficha (±2 dB). Tasa PHY = 2 flujos × 52 subportadoras × bits × codificación / 3.6 µs (canal 20 MHz, supuesto).
A4: Modulación | B4: Bits/símbolo | C4: Codificación | D4: Sensibilidad (dBm) | E4: Tx máx. (dBm) | F4: Tasa PHY 20 MHz (Mbps) | G4: Sens. + penalización (dBm)
A5: BPSK 1/2 | B5: 1 | C5: 0.5 | D5: -96 | E5: 28 | F5: =2*52*B5*C5/3.6 -> 14.444444 | G5: =D5+Supuestos!$C$14 -> -93
A6: QPSK 1/2 | B6: 2 | C6: 0.5 | D6: -95 | E6: 28 | F6: =2*52*B6*C6/3.6 -> 28.888889 | G6: =D6+Supuestos!$C$14 -> -92
A7: QPSK 3/4 | B7: 2 | C7: 0.75 | D7: -92 | E7: 28 | F7: =2*52*B7*C7/3.6 -> 43.333333 | G7: =D7+Supuestos!$C$14 -> -89
A8: 16QAM 1/2 | B8: 4 | C8: 0.5 | D8: -90 | E8: 28 | F8: =2*52*B8*C8/3.6 -> 57.777778 | G8: =D8+Supuestos!$C$14 -> -87
A9: 16QAM 3/4 | B9: 4 | C9: 0.75 | D9: -86 | E9: 28 | F9: =2*52*B9*C9/3.6 -> 86.666667 | G9: =D9+Supuestos!$C$14 -> -83
A10: 64QAM 2/3 | B10: 6 | C10: 0.66666667 | D10: -83 | E10: 28 | F10: =2*52*B10*C10/3.6 -> 115.55556 | G10: =D10+Supuestos!$C$14 -> -80
A11: 64QAM 3/4 | B11: 6 | C11: 0.75 | D11: -77 | E11: 27 | F11: =2*52*B11*C11/3.6 -> 130 | G11: =D11+Supuestos!$C$14 -> -74
A12: 64QAM 5/6 | B12: 6 | C12: 0.83333333 | D12: -74 | E12: 26 | F12: =2*52*B12*C12/3.6 -> 144.44444 | G12: =D12+Supuestos!$C$14 -> -71
A13: 256QAM 3/4 | B13: 8 | C13: 0.75 | D13: -69 | E13: 24 | F13: =2*52*B13*C13/3.6 -> 173.33333 | G13: =D13+Supuestos!$C$14 -> -66
A14: 256QAM 5/6 | B14: 8 | C14: 0.83333333 | D14: -65 | E14: 22 | F14: =2*52*B14*C14/3.6 -> 192.59259 | G14: =D14+Supuestos!$C$14 -> -62

Sheet Enlace_por_casa
A1: Presupuesto de enlace por casa (torre 30 m → CPE), bajada y subida
A2: Azul: datos de entrada por casa (georreferenciación, terreno y profundidad de follaje de rfmodel.py). Todas las demás columnas son fórmulas.
A4: Casa | B4: Acimut torre→casa (°) | C4: Distancia horiz. (m) | D4: Elev. terreno casa (m) | E4: Follaje atravesado (m) | F4: Sector | G4: Eje sector (°) | H4: Δ acimut (°) | I4: Desnivel antena–CPE (m) | J4: Distancia 3D (m) | K4: Elevación del rayo (°) | L4: Δ elev. respecto al haz (°) | M4: Pérd. patrón azimut (dB) | N4: u (apertura) | O4: Pérd. patrón elev. (dB) | P4: Ganancia AP efectiva (dBi) | Q4: FSPL (dB) | R4: Pérd. follaje Weissberger (dB) | S4: Pérdida total de trayecto (dB) | T4: Margen DL sobre BPSK (dB) | U4: Margen UL sobre BPSK (dB) | V4: N.º MCS útiles DL | W4: N.º MCS útiles UL | X4: MCS DL | Y4: Tasa DL (Mbps) | Z4: Tasa UL (Mbps) | AA4: Carga aire DL | AB4: Carga aire UL
A5: 1 | B5: 231.5 | C5: 297 | D5: 215.9 | E5: 31 | F5: =IF(AND(B5>=90,B5<210),"S1",IF(AND(B5>=210,B5<330),"S2","S3")) -> S2 | G5: =IF(F5="S1",Supuestos!$C$26,IF(F5="S2",Supuestos!$C$27,Supuestos!$C$28)) -> 270 | H5: =MOD(B5-G5+180,360)-180 -> -38.5 | I5: =Supuestos!$C$7-(D5-Supuestos!$C$8)-Supuestos!$C$9 -> 14.1 | J5: =SQRT(C5^2+I5^2) -> 297.33451 | K5: =DEGREES(ATAN2(C5,I5)) -> 2.7180619 | L5: =K5-(Supuestos!$C$21+Supuestos!$C$22) -> -1.2819381 | M5: =MIN(6*(2*H5/Supuestos!$C$20)^2,Supuestos!$C$24) -> 1.8953594 | N5: =PI()*Supuestos!$C$23/Supuestos!$C$6*SIN(RADIANS(L5)) -> -0.49903549 | O5: =IF(ABS(N5)<0.000000001,0,MIN(-20*LOG10(MAX(ABS(SIN(N5)/N5),0.000001)),Supuestos!$C$25)) -> 0.36355809 | P5: =Supuestos!$C$19-M5-O5 -> 13.241083 | Q5: =32.44+20*LOG10(J5/1000)+20*LOG10(Supuestos!$C$5*1000) -> 97.173466 | R5: =IF(E5<=0,0,IF(E5<=14,0.45*Supuestos!$C$5^0.284*E5,1.33*Supuestos!$C$5^0.284*MIN(E5,400)^0.588)) -> 16.503873 | S5: =Q5+R5+Supuestos!$C$12+Supuestos!$C$13+Supuestos!$C$11-P5-Supuestos!$C$10 -> 79.236256 | T5: =MCS!$E$5-S5-MCS!$G$5 -> 41.763744 | U5: =T5-Supuestos!$C$15 -> 38.763744 | V5: =SUMPRODUCT(--(MCS!$E$5:$E$14-$S5-MCS!$G$5:$G$14>=Supuestos!$C$16)) -> 9 | W5: =SUMPRODUCT(--(MCS!$E$5:$E$14-Supuestos!$C$15-$S5-MCS!$G$5:$G$14>=Supuestos!$C$16)) -> 8 | X5: =IF(V5=0,"ninguno",INDEX(MCS!$A$5:$A$14,V5)) -> 256QAM 3/4 | Y5: =IF(V5=0,0,INDEX(MCS!$F$5:$F$14,V5)) -> 173.33333 | Z5: =IF(W5=0,0,INDEX(MCS!$F$5:$F$14,W5)) -> 144.44444 | AA5: =IF(Y5>0,Supuestos!$C$29*Supuestos!$C$30/(Supuestos!$C$17*Y5),0) -> 0.0079881657 | AB5: =IF(Z5>0,Supuestos!$C$29*Supuestos!$C$31/(Supuestos!$C$17*Z5),0) -> 0.0011982249
A6: 2 | B6: 223.8 | C6: 233.3 | D6: 209 | E6: 42 | F6: =IF(AND(B6>=90,B6<210),"S1",IF(AND(B6>=210,B6<330),"S2","S3")) -> S2 | G6: =IF(F6="S1",Supuestos!$C$26,IF(F6="S2",Supuestos!$C$27,Supuestos!$C$28)) -> 270 | H6: =MOD(B6-G6+180,360)-180 -> -46.2 | I6: =Supuestos!$C$7-(D6-Supuestos!$C$8)-Supuestos!$C$9 -> 21 | J6: =SQRT(C6^2+I6^2) -> 234.24323 | K6: =DEGREES(ATAN2(C6,I6)) -> 5.1434954 | L6: =K6-(Supuestos!$C$21+Supuestos!$C$22) -> 1.1434954 | M6: =MIN(6*(2*H6/Supuestos!$C$20)^2,Supuestos!$C$24) -> 2.7293175 | N6: =PI()*Supuestos!$C$23/Supuestos!$C$6*SIN(RADIANS(L6)) -> 0.4451498 | O6: =IF(ABS(N6)<0.000000001,0,MIN(-20*LOG10(MAX(ABS(SIN(N6)/N6),0.000001)),Supuestos!$C$25)) -> 0.2887826 | P6: =Supuestos!$C$19-M6-O6 -> 12.4819 | Q6: =32.44+20*LOG10(J6/1000)+20*LOG10(Supuestos!$C$5*1000) -> 95.101901 | R6: =IF(E6<=0,0,IF(E6<=14,0.45*Supuestos!$C$5^0.284*E6,1.33*Supuestos!$C$5^0.284*MIN(E6,400)^0.588)) -> 19.730395 | S6: =Q6+R6+Supuestos!$C$12+Supuestos!$C$13+Supuestos!$C$11-P6-Supuestos!$C$10 -> 81.150396 | T6: =MCS!$E$5-S6-MCS!$G$5 -> 39.849604 | U6: =T6-Supuestos!$C$15 -> 36.849604 | V6: =SUMPRODUCT(--(MCS!$E$5:$E$14-$S6-MCS!$G$5:$G$14>=Supuestos!$C$16)) -> 8 | W6: =SUMPRODUCT(--(MCS!$E$5:$E$14-Supuestos!$C$15-$S6-MCS!$G$5:$G$14>=Supuestos!$C$16)) -> 8 | X6: =IF(V6=0,"ninguno",INDEX(MCS!$A$5:$A$14,V6)) -> 64QAM 5/6 | Y6: =IF(V6=0,0,INDEX(MCS!$F$5:$F$14,V6)) -> 144.44444 | Z6: =IF(W6=0,0,INDEX(MCS!$F$5:$F$14,W6)) -> 144.44444 | AA6: =IF(Y6>0,Supuestos!$C$29*Supuestos!$C$30/(Supuestos!$C$17*Y6),0) -> 0.0095857988 | AB6: =IF(Z6>0,Supuestos!$C$29*Supuestos!$C$31/(Supuestos!$C$17*Z6),0) -> 0.0011982249
A7: 3 | B7: 215.4 | C7: 201.1 | D7: 208.3 | E7: 81 | F7: =IF(AND(B7>=90,B7<210),"S1",IF(AND(B7>=210,B7<330),"S2","S3")) -> S2 | G7: =IF(F7="S1",Supuestos!$C$26,IF(F7="S2",Supuestos!$C$27,Supuestos!$C$28)) -> 270 | H7: =MOD(B7-G7+180,360)-180 -> -54.6 | I7: =Supuestos!$C$7-(D7-Supuestos!$C$8)-Supuestos!$C$9 -> 21.7 | J7: =SQRT(C7^2+I7^2) -> 202.2674 | K7: =DEGREES(ATAN2(C7,I7)) -> 6.1587578 | L7: =K7-(Supuestos!$C$21+Supuestos!$C$22) -> 2.1587578 | M7: =MIN(6*(2*H7/Supuestos!$C$20)^2,Supuestos!$C$24) -> 3.812022 | N7: =PI()*Supuestos!$C$23/Supuestos!$C$6*SIN(RADIANS(L7)) -> 0.84023691 | O7: =IF(ABS(N7)<0.000000001,0,MIN(-20*LOG10(MAX(ABS(SIN(N7)/N7),0.000001)),Supuestos!$C$25)) -> 1.0472274 | P7: =Supuestos!$C$19-M7-O7 -> 10.640751 | Q7: =32.44+20*LOG10(J7/1000)+20*LOG10(Supuestos!$C$5*1000) -> 93.827078 | R7: =IF(E7<=0,0,IF(E7<=14,0.45*Supuestos!$C$5^0.284*E7,1.33*Supuestos!$C$5^0.284*MIN(E7,400)^0.588)) -> 29.030491 | S7: =Q7+R7+Supuestos!$C$12+Supuestos!$C$13+Supuestos!$C$11-P7-Supuestos!$C$10 -> 91.016818 | T7: =MCS!$E$5-S7-MCS!$G$5 -> 29.983182 | U7: =T7-Supuestos!$C$15 -> 26.983182 | V7: =SUMPRODUCT(--(MCS!$E$5:$E$14-$S7-MCS!$G$5:$G$14>=Supuestos!$C$16)) -> 6 | W7: =SUMPRODUCT(--(MCS!$E$5:$E$14-Supuestos!$C$15-$S7-MCS!$G$5:$G$14>=Supuestos!$C$16)) -> 6 | X7: =IF(V7=0,"ninguno",INDEX(MCS!$A$5:$A$14,V7)) -> 64QAM 2/3 | Y7: =IF(V7=0,0,INDEX(MCS!$F$5:$F$14,V7)) -> 115.55556 | Z7: =IF(W7=0,0,INDEX(MCS!$F$5:$F$14,W7)) -> 115.55556 | AA7: =IF(Y7>0,Supuestos!$C$29*Supuestos!$C$30/(Supuestos!$C$17*Y7),0) -> 0.011982249 | AB7: =IF(Z7>0,Supuestos!$C$29*Supuestos!$C$31/(Supuestos!$C$17*Z7),0) -> 0.0014977811
A8: 4 | B8: 209.3 | C8: 189.9 | D8: 208.7 | E8: 55 | F8: =IF(AND(B8>=90,B8<210),"S1",IF(AND(B8>=210,B8<330),"S2","S3")) -> S1 | G8: =IF(F8="S1",Supuestos!$C$26,IF(F8="S2",Supuestos!$C$27,Supuestos!$C$28)) -> 150 | H8: =MOD(B8-G8+180,360)-180 -> 59.3 | I8: =Supuestos!$C$7-(D8-Supuestos!$C$8)-Supuestos!$C$9 -> 21.3 | J8: =SQRT(C8^2+I8^2) -> 191.09082 | K8: =DEGREES(ATAN2(C8,I8)) -> 6.399792 | L8: =K8-(Supuestos!$C$21+Supuestos!$C$22) -> 2.399792 | M8: =MIN(6*(2*H8/Supuestos!$C$20)^2,Supuestos!$C$24) -> 4.4965507 | N8: =PI()*Supuestos!$C$23/Supuestos!$C$6*SIN(RADIANS(L8)) -> 0.93400074 | O8: =IF(ABS(N8)<0.000000001,0,MIN(-20*LOG10(MAX(ABS(SIN(N8)/N8),0.000001)),Supuestos!$C$25)) -> 1.3017662 | P8: =Supuestos!$C$19-M8-O8 -> 9.7016831 | Q8: =32.44+20*LOG10(J8/1000)+20*LOG10(Supuestos!$C$5*1000) -> 93.333356 | R8: =IF(E8<=0,0,IF(E8<=14,0.45*Supuestos!$C$5^0.284*E8,1.33*Supuestos!$C$5^0.284*MIN(E8,400)^0.588)) -> 23.120566 | S8: =Q8+R8+Supuestos!$C$12+Supuestos!$C$13+Supuestos!$C$11-P8-Supuestos!$C$10 -> 85.552239 | T8: =MCS!$E$5-S8-MCS!$G$5 -> 35.447761 | U8: =T8-Supuestos!$C$15 -> 32.447761 | V8: =SUMPRODUCT(--(MCS!$E$5:$E$14-$S8-MCS!$G$5:$G$14>=Supuestos!$C$16)) -> 8 | W8: =SUMPRODUCT(--(MCS!$E$5:$E$14-Supuestos!$C$15-$S8-MCS!$G$5:$G$14>=Supuestos!$C$16)) -> 7 | X8: =IF(V8=0,"ninguno",INDEX(MCS!$A$5:$A$14,V8)) -> 64QAM 5/6 | Y8: =IF(V8=0,0,INDEX(MCS!$F$5:$F$14,V8)) -> 144.44444 | Z8: =IF(W8=0,0,INDEX(MCS!$F$5:$F$14,W8)) -> 130 | AA8: =IF(Y8>0,Supuestos!$C$29*Supuestos!$C$30/(Supuestos!$C$17*Y8),0) -> 0.0095857988 | AB8: =IF(Z8>0,Supuestos!$C$29*Supuestos!$C$31/(Supuestos!$C$17*Z8),0) -> 0.0013313609
A9: 5 | B9: 233.2 | C9: 209.2 | D9: 205.9 | E9: 85 | F9: =IF(AND(B9>=90,B9<210),"S1",IF(AND(B9>=210,B9<330),"S2","S3")) -> S2 | G9: =IF(F9="S1",Supuestos!$C$26,IF(F9="S2",Supuestos!$C$27,Supuestos!$C$28)) -> 270 | H9: =MOD(B9-G9+180,360)-180 -> -36.8 | I9: =Supuestos!$C$7-(D9-Supuestos!$C$8)-Supuestos!$C$9 -> 24.1 | J9: =SQRT(C9^2+I9^2) -> 210.58359 | K9: =DEGREES(ATAN2(C9,I9)) -> 6.571549 | L9: =K9-(Supuestos!$C$21+Supuestos!$C$22) -> 2.571549 | M9: =MIN(6*(2*H9/Supuestos!$C$20)^2,Supuestos!$C$24) -> 1.7316724 | N9: =PI()*Supuestos!$C$23/Supuestos!$C$6*SIN(RADIANS(L9)) -> 1.0008053 | O9: =IF(ABS(N9)<0.000000001,0,MIN(-20*LOG10(MAX(ABS(SIN(N9)/N9),0.000001)),Supuestos!$C$25)) -> 1.5017216 | P9: =Supuestos!$C$19-M9-O9 -> 12.266606 | Q9: =32.44+20*LOG10(J9/1000)+20*LOG10(Supuestos!$C$5*1000) -> 94.177051 | R9: =IF(E9<=0,0,IF(E9<=14,0.45*Supuestos!$C$5^0.284*E9,1.33*Supuestos!$C$5^0.284*MIN(E9,400)^0.588)) -> 29.865069 | S9: =Q9+R9+Supuestos!$C$12+Supuestos!$C$13+Supuestos!$C$11-P9-Supuestos!$C$10 -> 90.575513 | T9: =MCS!$E$5-S9-MCS!$G$5 -> 30.424487 | U9: =T9-Supuestos!$C$15 -> 27.424487 | V9: =SUMPRODUCT(--(MCS!$E$5:$E$14-$S9-MCS!$G$5:$G$14>=Supuestos!$C$16)) -> 7 | W9: =SUMPRODUCT(--(MCS!$E$5:$E$14-Supuestos!$C$15-$S9-MCS!$G$5:$G$14>=Supuestos!$C$16)) -> 6 | X9: =IF(V9=0,"ninguno",INDEX(MCS!$A$5:$A$14,V9)) -> 64QAM 3/4 | Y9: =IF(V9=0,0,INDEX(MCS!$F$5:$F$14,V9)) -> 130 | Z9: =IF(W9=0,0,INDEX(MCS!$F$5:$F$14,W9)) -> 115.55556 | AA9: =IF(Y9>0,Supuestos!$C$29*Supuestos!$C$30/(Supuestos!$C$17*Y9),0) -> 0.010650888 | AB9: =IF(Z9>0,Supuestos!$C$29*Supuestos!$C$31/(Supuestos!$C$17*Z9),0) -> 0.0014977811
A10: 6 | B10: 239.3 | C10: 184.9 | D10: 205.3 | E10: 82 | F10: =IF(AND(B10>=90,B10<210),"S1",IF(AND(B10>=210,B10<330),"S2","S3")) -> S2 | G10: =IF(F10="S1",Supuestos!$C$26,IF(F10="S2",Supuestos!$C$27,Supuestos!$C$28)) -> 270 | H10: =MOD(B10-G10+180,360)-180 -> -30.7 | I10: =Supuestos!$C$7-(D10-Supuestos!$C$8)-Supuestos!$C$9 -> 24.7 | J10: =SQRT(C10^2+I10^2) -> 186.54249 | K10: =DEGREES(ATAN2(C10,I10)) -> 7.6088511 | L10: =K10-(Supuestos!$C$21+Supuestos!$C$22) -> 3.6088511 | M10: =MIN(6*(2*H10/Supuestos!$C$20)^2,Supuestos!$C$24) -> 1.205166 | N10: =PI()*Supuestos!$C$23/Supuestos!$C$6*SIN(RADIANS(L10)) -> 1.4040493 | O10: =IF(ABS(N10)<0.000000001,0,MIN(-20*LOG10(MAX(ABS(SIN(N10)/N10),0.000001)),Supuestos!$C$25)) -> 3.0689647 | P10: =Supuestos!$C$19-M10-O10 -> 11.225869 | Q10: =32.44+20*LOG10(J10/1000)+20*LOG10(Supuestos!$C$5*1000) -> 93.124115 | R10: =IF(E10<=0,0,IF(E10<=14,0.45*Supuestos!$C$5^0.284*E10,1.33*Supuestos!$C$5^0.284*MIN(E10,400)^0.588)) -> 29.240698 | S10: =Q10+R10+Supuestos!$C$12+Supuestos!$C$13+Supuestos!$C$11-P10-Supuestos!$C$10 -> 89.938944 | T10: =MCS!$E$5-S10-MCS!$G$5 -> 31.061056 | U10: =T10-Supuestos!$C$15 -> 28.061056 | V10: =SUMPRODUCT(--(MCS!$E$5:$E$14-$S10-MCS!$G$5:$G$14>=Supuestos!$C$16)) -> 7 | W10: =SUMPRODUCT(--(MCS!$E$5:$E$14-Supuestos!$C$15-$S10-MCS!$G$5:$G$14>=Supuestos!$C$16)) -> 6 | X10: =IF(V10=0,"ninguno",INDEX(MCS!$A$5:$A$14,V10)) -> 64QAM 3/4 | Y10: =IF(V10=0,0,INDEX(MCS!$F$5:$F$14,V10)) -> 130 | Z10: =IF(W10=0,0,INDEX(MCS!$F$5:$F$14,W10)) -> 115.55556 | AA10: =IF(Y10>0,Supuestos!$C$29*Supuestos!$C$30/(Supuestos!$C$17*Y10),0) -> 0.010650888 | AB10: =IF(Z10>0,Supuestos!$C$29*Supuestos!$C$31/(Supuestos!$C$17*Z10),0) -> 0.0014977811
A11: 7 | B11: 243.7 | C11: 217.1 | D11: 206.4 | E11: 58 | F11: =IF(AND(B11>=90,B11<210),"S1",IF(AND(B11>=210,B11<330),"S2","S3")) -> S2 | G11: =IF(F11="S1",Supuestos!$C$26,IF(F11="S2",Supuestos!$C$27,Supuestos!$C$28)) -> 270 | H11: =MOD(B11-G11+180,360)-180 -> -26.3 | I11: =Supuestos!$C$7-(D11-Supuestos!$C$8)-Supuestos!$C$9 -> 23.6 | J11: =SQRT(C11^2+I11^2) -> 218.37896 | K11: =DEGREES(ATAN2(C11,I11)) -> 6.2040149 | L11: =K11-(Supuestos!$C$21+Supuestos!$C$22) -> 2.2040149 | M11: =MIN(6*(2*H11/Supuestos!$C$20)^2,Supuestos!$C$24) -> 0.88446694 | N11: =PI()*Supuestos!$C$23/Supuestos!$C$6*SIN(RADIANS(L11)) -> 0.8578434 | O11: =IF(ABS(N11)<0.000000001,0,MIN(-20*LOG10(MAX(ABS(SIN(N11)/N11),0.000001)),Supuestos!$C$25)) -> 1.0927423 | P11: =Supuestos!$C$19-M11-O11 -> 13.522791 | Q11: =32.44+20*LOG10(J11/1000)+20*LOG10(Supuestos!$C$5*1000) -> 94.492776 | R11: =IF(E11<=0,0,IF(E11<=14,0.45*Supuestos!$C$5^0.284*E11,1.33*Supuestos!$C$5^0.284*MIN(E11,400)^0.588)) -> 23.85398 | S11: =Q11+R11+Supuestos!$C$12+Supuestos!$C$13+Supuestos!$C$11-P11-Supuestos!$C$10 -> 83.623965 | T11: =MCS!$E$5-S11-MCS!$G$5 -> 37.376035 | U11: =T11-Supuestos!$C$15 -> 34.376035 | V11: =SUMPRODUCT(--(MCS!$E$5:$E$14-$S11-MCS!$G$5:$G$14>=Supuestos!$C$16)) -> 8 | W11: =SUMPRODUCT(--(MCS!$E$5:$E$14-Supuestos!$C$15-$S11-MCS!$G$5:$G$14>=Supuestos!$C$16)) -> 8 | X11: =IF(V11=0,"ninguno",INDEX(MCS!$A$5:$A$14,V11)) -> 64QAM 5/6 | Y11: =IF(V11=0,0,INDEX(MCS!$F$5:$F$14,V11)) -> 144.44444 | Z11: =IF(W11=0,0,INDEX(MCS!$F$5:$F$14,W11)) -> 144.44444 | AA11: =IF(Y11>0,Supuestos!$C$29*Supuestos!$C$30/(Supuestos!$C$17*Y11),0) -> 0.0095857988 | AB11: =IF(Z11>0,Supuestos!$C$29*Supuestos!$C$31/(Supuestos!$C$17*Z11),0) -> 0.0011982249
A12: 8 | B12: 252.2 | C12: 268.8 | D12: 211.1 | E12: 65 | F12: =IF(AND(B12>=90,B12<210),"S1",IF(AND(B12>=210,B12<330),"S2","S3")) -> S2 | G12: =IF(F12="S1",Supuestos!$C$26,IF(F12="S2",Supuestos!$C$27,Supuestos!$C$28)) -> 270 | H12: =MOD(B12-G12+180,360)-180 -> -17.8 | I12: =Supuestos!$C$7-(D12-Supuestos!$C$8)-Supuestos!$C$9 -> 18.9 | J12: =SQRT(C12^2+I12^2) -> 269.46363 | K12: =DEGREES(ATAN2(C12,I12)) -> 4.0219902 | L12: =K12-(Supuestos!$C$21+Supuestos!$C$22) -> 0.021990177 | M12: =MIN(6*(2*H12/Supuestos!$C$20)^2,Supuestos!$C$24) -> 0.40514465 | N12: =PI()*Supuestos!$C$23/Supuestos!$C$6*SIN(RADIANS(L12)) -> 0.0085610949 | O12: =IF(ABS(N12)<0.000000001,0,MIN(-20*LOG10(MAX(ABS(SIN(N12)/N12),0.000001)),Supuestos!$C$25)) -> 0.0001061018 | P12: =Supuestos!$C$19-M12-O12 -> 15.094749 | Q12: =32.44+20*LOG10(J12/1000)+20*LOG10(Supuestos!$C$5*1000) -> 96.318563 | R12: =IF(E12<=0,0,IF(E12<=14,0.45*Supuestos!$C$5^0.284*E12,1.33*Supuestos!$C$5^0.284*MIN(E12,400)^0.588)) -> 25.506933 | S12: =Q12+R12+Supuestos!$C$12+Supuestos!$C$13+Supuestos!$C$11-P12-Supuestos!$C$10 -> 85.530747 | T12: =MCS!$E$5-S12-MCS!$G$5 -> 35.469253 | U12: =T12-Supuestos!$C$15 -> 32.469253 | V12: =SUMPRODUCT(--(MCS!$E$5:$E$14-$S12-MCS!$G$5:$G$14>=Supuestos!$C$16)) -> 8 | W12: =SUMPRODUCT(--(MCS!$E$5:$E$14-Supuestos!$C$15-$S12-MCS!$G$5:$G$14>=Supuestos!$C$16)) -> 7 | X12: =IF(V12=0,"ninguno",INDEX(MCS!$A$5:$A$14,V12)) -> 64QAM 5/6 | Y12: =IF(V12=0,0,INDEX(MCS!$F$5:$F$14,V12)) -> 144.44444 | Z12: =IF(W12=0,0,INDEX(MCS!$F$5:$F$14,W12)) -> 130 | AA12: =IF(Y12>0,Supuestos!$C$29*Supuestos!$C$30/(Supuestos!$C$17*Y12),0) -> 0.0095857988 | AB12: =IF(Z12>0,Supuestos!$C$29*Supuestos!$C$31/(Supuestos!$C$17*Z12),0) -> 0.0013313609
A13: 9 | B13: 250 | C13: 294.8 | D13: 214.9 | E13: 50 | F13: =IF(AND(B13>=90,B13<210),"S1",IF(AND(B13>=210,B13<330),"S2","S3")) -> S2 | G13: =IF(F13="S1",Supuestos!$C$26,IF(F13="S2",Supuestos!$C$27,Supuestos!$C$28)) -> 270 | H13: =MOD(B13-G13+180,360)-180 -> -20 | I13: =Supuestos!$C$7-(D13-Supuestos!$C$8)-Supuestos!$C$9 -> 15.1 | J13: =SQRT(C13^2+I13^2) -> 295.18647 | K13: =DEGREES(ATAN2(C13,I13)) -> 2.9321942 | L13: =K13-(Supuestos!$C$21+Supuestos!$C$22) -> -1.0678058 | M13: =MIN(6*(2*H13/Supuestos!$C$20)^2,Supuestos!$C$24) -> 0.5114817 | N13: =PI()*Supuestos!$C$23/Supuestos!$C$6*SIN(RADIANS(L13)) -> -0.41568824 | O13: =IF(ABS(N13)<0.000000001,0,MIN(-20*LOG10(MAX(ABS(SIN(N13)/N13),0.000001)),Supuestos!$C$25)) -> 0.25160571 | P13: =Supuestos!$C$19-M13-O13 -> 14.736913 | Q13: =32.44+20*LOG10(J13/1000)+20*LOG10(Supuestos!$C$5*1000) -> 97.110489 | R13: =IF(E13<=0,0,IF(E13<=14,0.45*Supuestos!$C$5^0.284*E13,1.33*Supuestos!$C$5^0.284*MIN(E13,400)^0.588)) -> 21.860473 | S13: =Q13+R13+Supuestos!$C$12+Supuestos!$C$13+Supuestos!$C$11-P13-Supuestos!$C$10 -> 83.034049 | T13: =MCS!$E$5-S13-MCS!$G$5 -> 37.965951 | U13: =T13-Supuestos!$C$15 -> 34.965951 | V13: =SUMPRODUCT(--(MCS!$E$5:$E$14-$S13-MCS!$G$5:$G$14>=Supuestos!$C$16)) -> 8 | W13: =SUMPRODUCT(--(MCS!$E$5:$E$14-Supuestos!$C$15-$S13-MCS!$G$5:$G$14>=Supuestos!$C$16)) -> 8 | X13: =IF(V13=0,"ninguno",INDEX(MCS!$A$5:$A$14,V13)) -> 64QAM 5/6 | Y13: =IF(V13=0,0,INDEX(MCS!$F$5:$F$14,V13)) -> 144.44444 | Z13: =IF(W13=0,0,INDEX(MCS!$F$5:$F$14,W13)) -> 144.44444 | AA13: =IF(Y13>0,Supuestos!$C$29*Supuestos!$C$30/(Supuestos!$C$17*Y13),0) -> 0.0095857988 | AB13: =IF(Z13>0,Supuestos!$C$29*Supuestos!$C$31/(Supuestos!$C$17*Z13),0) -> 0.0011982249
A14: 10 | B14: 255 | C14: 286.9 | D14: 213 | E14: 69 | F14: =IF(AND(B14>=90,B14<210),"S1",IF(AND(B14>=210,B14<330),"S2","S3")) -> S2 | G14: =IF(F14="S1",Supuestos!$C$26,IF(F14="S2",Supuestos!$C$27,Supuestos!$C$28)) -> 270 | H14: =MOD(B14-G14+180,360)-180 -> -15 | I14: =Supuestos!$C$7-(D14-Supuestos!$C$8)-Supuestos!$C$9 -> 17 | J14: =SQRT(C14^2+I14^2) -> 287.40322 | K14: =DEGREES(ATAN2(C14,I14)) -> 3.3910446 | L14: =K14-(Supuestos!$C$21+Supuestos!$C$22) -> -0.60895541 | M14: =MIN(6*(2*H14/Supuestos!$C$20)^2,Supuestos!$C$24) -> 0.28770846 | N14: =PI()*Supuestos!$C$23/Supuestos!$C$6*SIN(RADIANS(L14)) -> -0.23707071 | O14: =IF(ABS(N14)<0.000000001,0,MIN(-20*LOG10(MAX(ABS(SIN(N14)/N14),0.000001)),Supuestos!$C$25)) -> 0.081514457 | P14: =Supuestos!$C$19-M14-O14 -> 15.130777 | Q14: =32.44+20*LOG10(J14/1000)+20*LOG10(Supuestos!$C$5*1000) -> 96.878392 | R14: =IF(E14<=0,0,IF(E14<=14,0.45*Supuestos!$C$5^0.284*E14,1.33*Supuestos!$C$5^0.284*MIN(E14,400)^0.588)) -> 26.418518 | S14: =Q14+R14+Supuestos!$C$12+Supuestos!$C$13+Supuestos!$C$11-P14-Supuestos!$C$10 -> 86.966134 | T14: =MCS!$E$5-S14-MCS!$G$5 -> 34.033866 | U14: =T14-Supuestos!$C$15 -> 31.033866 | V14: =SUMPRODUCT(--(MCS!$E$5:$E$14-$S14-MCS!$G$5:$G$14>=Supuestos!$C$16)) -> 8 | W14: =SUMPRODUCT(--(MCS!$E$5:$E$14-Supuestos!$C$15-$S14-MCS!$G$5:$G$14>=Supuestos!$C$16)) -> 7 | X14: =IF(V14=0,"ninguno",INDEX(MCS!$A$5:$A$14,V14)) -> 64QAM 5/6 | Y14: =IF(V14=0,0,INDEX(MCS!$F$5:$F$14,V14)) -> 144.44444 | Z14: =IF(W14=0,0,INDEX(MCS!$F$5:$F$14,W14)) -> 130 | AA14: =IF(Y14>0,Supuestos!$C$29*Supuestos!$C$30/(Supuestos!$C$17*Y14),0) -> 0.0095857988 | AB14: =IF(Z14>0,Supuestos!$C$29*Supuestos!$C$31/(Supuestos!$C$17*Z14),0) -> 0.0013313609
A15: 11 | B15: 256.5 | C15: 321.6 | D15: 217.3 | E15: 32 | F15: =IF(AND(B15>=90,B15<210),"S1",IF(AND(B15>=210,B15<330),"S2","S3")) -> S2 | G15: =IF(F15="S1",Supuestos!$C$26,IF(F15="S2",Supuestos!$C$27,Supuestos!$C$28)) -> 270 | H15: =MOD(B15-G15+180,360)-180 -> -13.5 | I15: =Supuestos!$C$7-(D15-Supuestos!$C$8)-Supuestos!$C$9 -> 12.7 | J15: =SQRT(C15^2+I15^2) -> 321.85066 | K15: =DEGREES(ATAN2(C15,I15)) -> 2.2614381 | L15: =K15-(Supuestos!$C$21+Supuestos!$C$22) -> -1.7385619 | M15: =MIN(6*(2*H15/Supuestos!$C$20)^2,Supuestos!$C$24) -> 0.23304385 | N15: =PI()*Supuestos!$C$23/Supuestos!$C$6*SIN(RADIANS(L15)) -> -0.67674351 | O15: =IF(ABS(N15)<0.000000001,0,MIN(-20*LOG10(MAX(ABS(SIN(N15)/N15),0.000001)),Supuestos!$C$25)) -> 0.67342268 | P15: =Supuestos!$C$19-M15-O15 -> 14.593533 | Q15: =32.44+20*LOG10(J15/1000)+20*LOG10(Supuestos!$C$5*1000) -> 97.861648 | R15: =IF(E15<=0,0,IF(E15<=14,0.45*Supuestos!$C$5^0.284*E15,1.33*Supuestos!$C$5^0.284*MIN(E15,400)^0.588)) -> 16.814865 | S15: =Q15+R15+Supuestos!$C$12+Supuestos!$C$13+Supuestos!$C$11-P15-Supuestos!$C$10 -> 78.882979 | T15: =MCS!$E$5-S15-MCS!$G$5 -> 42.117021 | U15: =T15-Supuestos!$C$15 -> 39.117021 | V15: =SUMPRODUCT(--(MCS!$E$5:$E$14-$S15-MCS!$G$5:$G$14>=Supuestos!$C$16)) -> 9 | W15: =SUMPRODUCT(--(MCS!$E$5:$E$14-Supuestos!$C$15-$S15-MCS!$G$5:$G$14>=Supuestos!$C$16)) -> 8 | X15: =IF(V15=0,"ninguno",INDEX(MCS!$A$5:$A$14,V15)) -> 256QAM 3/4 | Y15: =IF(V15=0,0,INDEX(MCS!$F$5:$F$14,V15)) -> 173.33333 | Z15: =IF(W15=0,0,INDEX(MCS!$F$5:$F$14,W15)) -> 144.44444 | AA15: =IF(Y15>0,Supuestos!$C$29*Supuestos!$C$30/(Supuestos!$C$17*Y15),0) -> 0.0079881657 | AB15: =IF(Z15>0,Supuestos!$C$29*Supuestos!$C$31/(Supuestos!$C$17*Z15),0) -> 0.0011982249
A16: 12 | B16: 260.1 | C16: 313.6 | D16: 214.8 | E16: 54 | F16: =IF(AND(B16>=90,B16<210),"S1",IF(AND(B16>=210,B16<330),"S2","S3")) -> S2 | G16: =IF(F16="S1",Supuestos!$C$26,IF(F16="S2",Supuestos!$C$27,Supuestos!$C$28)) -> 270 | H16: =MOD(B16-G16+180,360)-180 -> -9.9 | I16: =Supuestos!$C$7-(D16-Supuestos!$C$8)-Supuestos!$C$9 -> 15.2 | J16: =SQRT(C16^2+I16^2) -> 313.96815 | K16: =DEGREES(ATAN2(C16,I16)) -> 2.7749197 | L16: =K16-(Supuestos!$C$21+Supuestos!$C$22) -> -1.2250803 | M16: =MIN(6*(2*H16/Supuestos!$C$20)^2,Supuestos!$C$24) -> 0.1253258 | N16: =PI()*Supuestos!$C$23/Supuestos!$C$6*SIN(RADIANS(L16)) -> -0.47690521 | O16: =IF(ABS(N16)<0.000000001,0,MIN(-20*LOG10(MAX(ABS(SIN(N16)/N16),0.000001)),Supuestos!$C$25)) -> 0.33178388 | P16: =Supuestos!$C$19-M16-O16 -> 15.04289 | Q16: =32.44+20*LOG10(J16/1000)+20*LOG10(Supuestos!$C$5*1000) -> 97.646272 | R16: =IF(E16<=0,0,IF(E16<=14,0.45*Supuestos!$C$5^0.284*E16,1.33*Supuestos!$C$5^0.284*MIN(E16,400)^0.588)) -> 22.872452 | S16: =Q16+R16+Supuestos!$C$12+Supuestos!$C$13+Supuestos!$C$11-P16-Supuestos!$C$10 -> 84.275833 | T16: =MCS!$E$5-S16-MCS!$G$5 -> 36.724167 | U16: =T16-Supuestos!$C$15 -> 33.724167 | V16: =SUMPRODUCT(--(MCS!$E$5:$E$14-$S16-MCS!$G$5:$G$14>=Supuestos!$C$16)) -> 8 | W16: =SUMPRODUCT(--(MCS!$E$5:$E$14-Supuestos!$C$15-$S16-MCS!$G$5:$G$14>=Supuestos!$C$16)) -> 7 | X16: =IF(V16=0,"ninguno",INDEX(MCS!$A$5:$A$14,V16)) -> 64QAM 5/6 | Y16: =IF(V16=0,0,INDEX(MCS!$F$5:$F$14,V16)) -> 144.44444 | Z16: =IF(W16=0,0,INDEX(MCS!$F$5:$F$14,W16)) -> 130 | AA16: =IF(Y16>0,Supuestos!$C$29*Supuestos!$C$30/(Supuestos!$C$17*Y16),0) -> 0.0095857988 | AB16: =IF(Z16>0,Supuestos!$C$29*Supuestos!$C$31/(Supuestos!$C$17*Z16),0) -> 0.0013313609
... A113: 109 | B113: 99 | C113: 404.6 | D113: 236.1 | E113: 0 | F113: =IF(AND(B113>=90,B113<210),"S1",IF(AND(B113>=210,B113<330),"S2","S3")) -> S1 | G113: =IF(F113="S1",Supuestos!$C$26,IF(F113="S2",Supuestos!$C$27,Supuestos!$C$28)) -> 150 | H113: =MOD(B113-G113+180,360)-180 -> -51 | I113: =Supuestos!$C$7-(D113-Supuestos!$C$8)-Supuestos!$C$9 -> -6.1 | J113: =SQRT(C113^2+I113^2) -> 404.64598 | K113: =DEGREES(ATAN2(C113,I113)) -> -0.86376119 | L113: =K113-(Supuestos!$C$21+Supuestos!$C$22) -> -4.8637612 | M113: =MIN(6*(2*H113/Supuestos!$C$20)^2,Supuestos!$C$24) -> 3.3259097 | N113: =PI()*Supuestos!$C$23/Supuestos!$C$6*SIN(RADIANS(L113)) -> -1.8912595 | O113: =IF(ABS(N113)<0.000000001,0,MIN(-20*LOG10(MAX(ABS(SIN(N113)/N113),0.000001)),Supuestos!$C$25)) -> 5.9888779 | P113: =Supuestos!$C$19-M113-O113 -> 6.1852124 | Q113: =32.44+20*LOG10(J113/1000)+20*LOG10(Supuestos!$C$5*1000) -> 99.850064 | R113: =IF(E113<=0,0,IF(E113<=14,0.45*Supuestos!$C$5^0.284*E113,1.33*Supuestos!$C$5^0.284*MIN(E113,400)^0.588)) -> 0 | S113: =Q113+R113+Supuestos!$C$12+Supuestos!$C$13+Supuestos!$C$11-P113-Supuestos!$C$10 -> 72.464852 | T113: =MCS!$E$5-S113-MCS!$G$5 -> 48.535148 | U113: =T113-Supuestos!$C$15 -> 45.535148 | V113: =SUMPRODUCT(--(MCS!$E$5:$E$14-$S113-MCS!$G$5:$G$14>=Supuestos!$C$16)) -> 10 | W113: =SUMPRODUCT(--(MCS!$E$5:$E$14-Supuestos!$C$15-$S113-MCS!$G$5:$G$14>=Supuestos!$C$16)) -> 9 | X113: =IF(V113=0,"ninguno",INDEX(MCS!$A$5:$A$14,V113)) -> 256QAM 5/6 | Y113: =IF(V113=0,0,INDEX(MCS!$F$5:$F$14,V113)) -> 192.59259 | Z113: =IF(W113=0,0,INDEX(MCS!$F$5:$F$14,W113)) -> 173.33333 | AA113: =IF(Y113>0,Supuestos!$C$29*Supuestos!$C$30/(Supuestos!$C$17*Y113),0) -> 0.0071893491 | AB113: =IF(Z113>0,Supuestos!$C$29*Supuestos!$C$31/(Supuestos!$C$17*Z113),0) -> 0.00099852071

Sheet Capacidad
A1: Capacidad por sector y backhaul Starlink
A2: Utilización de aire = suma(demanda / (η_MAC · tasa PHY de cada casa)) / fracción de trama. Menor a 100 % = la demanda cabe.
A4: Sector | B4: Casas | C4: Suscriptores (adopción) | D4: Util. aire bajada | E4: Util. aire subida | F4: Nota
A5: S1 | B5: =COUNTIF(Enlace_por_casa!$F$5:$F$113,A5) -> 38 | C5: =B5*Supuestos!$C$29 -> 34.2 | D5: =SUMIF(Enlace_por_casa!$F$5:$F$113,A5,Enlace_por_casa!$AA$5:$AA$113)/Supuestos!$C$18 -> 0.43739645 | E5: =SUMIF(Enlace_por_casa!$F$5:$F$113,A5,Enlace_por_casa!$AB$5:$AB$113)/(1-Supuestos!$C$18) -> 0.17720414 | F5: Año 3 (90 % de adopción, 4 Mbps de pico por usuario activo, 25 % simultaneidad)
A6: S2 | B6: =COUNTIF(Enlace_por_casa!$F$5:$F$113,A6) -> 39 | C6: =B6*Supuestos!$C$29 -> 35.1 | D6: =SUMIF(Enlace_por_casa!$F$5:$F$113,A6,Enlace_por_casa!$AA$5:$AA$113)/Supuestos!$C$18 -> 0.4835503 | E6: =SUMIF(Enlace_por_casa!$F$5:$F$113,A6,Enlace_por_casa!$AB$5:$AB$113)/(1-Supuestos!$C$18) -> 0.20636095
A7: S3 | B7: =COUNTIF(Enlace_por_casa!$F$5:$F$113,A7) -> 32 | C7: =B7*Supuestos!$C$29 -> 28.8 | D7: =SUMIF(Enlace_por_casa!$F$5:$F$113,A7,Enlace_por_casa!$AA$5:$AA$113)/Supuestos!$C$18 -> 0.33976331 | E7: =SUMIF(Enlace_por_casa!$F$5:$F$113,A7,Enlace_por_casa!$AB$5:$AB$113)/(1-Supuestos!$C$18) -> 0.13113905
A9: Escenarios de crecimiento (escala lineal sobre la utilización base)
A10: Escenario | B10: Adopción | C10: Pico por usuario activo (Mbps) | D10: Util. S1 | E10: Util. S2 | F10: Util. S3
A11: Año 1 | B11: 0.6 | C11: 4 | D11: =$D$5*(B11/Supuestos!$C$29)*(C11/(4)) -> 0.29159763 | E11: =$D$6*(B11/Supuestos!$C$29)*(C11/(4)) -> 0.32236686 | F11: =$D$7*(B11/Supuestos!$C$29)*(C11/(4)) -> 0.22650888
A12: Año 3 (base) | B12: 0.9 | C12: 4 | D12: =$D$5*(B12/Supuestos!$C$29)*(C12/(4)) -> 0.43739645 | E12: =$D$6*(B12/Supuestos!$C$29)*(C12/(4)) -> 0.4835503 | F12: =$D$7*(B12/Supuestos!$C$29)*(C12/(4)) -> 0.33976331
A13: Año 5, 6 Mbps | B13: 1 | C13: 6 | D13: =$D$5*(B13/Supuestos!$C$29)*(C13/(4)) -> 0.72899408 | E13: =$D$6*(B13/Supuestos!$C$29)*(C13/(4)) -> 0.80591716 | F13: =$D$7*(B13/Supuestos!$C$29)*(C13/(4)) -> 0.56627219
A14: Año 5, 8 Mbps | B14: 1 | C14: 8 | D14: =$D$5*(B14/Supuestos!$C$29)*(C14/(4)) -> 0.97199211 | E14: =$D$6*(B14/Supuestos!$C$29)*(C14/(4)) -> 1.0745562 | F14: =$D$7*(B14/Supuestos!$C$29)*(C14/(4)) -> 0.75502959
A16: Backhaul Starlink
A17: Concepto | B17: Año 1 | C17: Año 3 | D17: Unidad | F17: Nota
A18: Puntos con CPE | B18: 65 | C18: 98 | D18: casas | F18: D04: 60 % / 90 % de 109 + 2 hotspots
A19: Simultaneidad pico | B19: 0.25 | C19: 0.25 | F19: Supuesto
A20: Tasa por usuario activo bajada | B20: 4 | C20: 4 | D20: Mbps | F20: Supuesto (video SD/HD, mensajería)
A21: Tasa por usuario activo subida | B21: 0.5 | C21: 0.5 | D21: Mbps | F21: Supuesto
A22: Pico agregado bajada | B22: =B18*B19*B20 -> 65 | C22: =C18*C19*C20 -> 98 | D22: Mbps
A23: Pico agregado subida | B23: =B18*B19*B21 -> 8.125 | C23: =C18*C19*C21 -> 12.25 | D23: Mbps
A24: Starlink bajada (diseño, límite inferior) | B24: 145 | C24: 145 | D24: Mbps | F24: F09 (captura starlink.com 23-oct-2026)
A25: Starlink subida (diseño) | B25: 21 | C25: 21 | D25: Mbps | F25: F11
A26: Uso del backhaul bajada | B26: =B22/B24 -> 0.44827586 | C26: =C22/C24 -> 0.67586207
A27: Uso del backhaul subida | B27: =B23/B25 -> 0.38690476 | C27: =C23/C25 -> 0.58333333
A28: Consumo mensual por punto (GB) | B28: 25 | C28: 25 | F28: Supuesto
A29: Consumo mensual total (TB) | B29: =B18*B28/1000 -> 1.625 | C29: =C18*C28/1000 -> 2.45

Sheet Interferencia
A1: Plan de frecuencias e interferencia entre sectores
A2: Resultados de analisis_e3.py (modelo C/I entre sectores; ruido −95 dBm; rechazo de canal adyacente 30 dB, supuestos). Valores calculados fuera de Excel.
A4: Sector | B4: Canal (MHz) | C4: Ancho (MHz) | D4: Eje (°) | E4: Polarización | F4: Sincronía
A5: S1 | B5: 5745 | C5: 20 | D5: 150 | E5: Doble (H/V) | F5: GPS
A6: S2 | B6: 5785 | C6: 20 | D6: 270 | E6: Doble (H/V) | F6: GPS | I6: Resumen
A7: S3 | B7: 5825 | C7: 20 | D7: 30 | E7: Doble (H/V) | F7: GPS | I7: C/I cocanal mínimo (dB) | J7: =MIN(C11:C119) -> 0
I8: C/I cocanal mediana (dB) | J8: =MEDIAN(C11:C119) -> 8
I9: Casas sin MCS útil: plan 3 canales | J9: =COUNTIF(D11:D119,"ninguno") -> 0
A10: Casa | B10: Sector | C10: C/I cocanal (dB) | D10: MCS plan 3 canales | E10: Tasa plan (Mbps) | F10: MCS con 1 solo canal | G10: Tasa 1 canal (Mbps) | I10: Casas sin MCS útil: 1 solo canal | J10: =COUNTIF(F11:F119,"ninguno") -> 40
A11: 1 | B11: S2 | C11: 6.5 | D11: 256QAM 3/4 | E11: 173.3 | F11: QPSK 1/2 | G11: 28.9
A12: 2 | B12: S2 | C12: 4.2 | D12: 64QAM 5/6 | E12: 144.4 | F12: ninguno | G12: 0
A13: 3 | B13: S2 | C13: 1.6 | D13: 64QAM 3/4 | E13: 130 | F13: ninguno | G13: 0
A14: 4 | B14: S1 | C14: 0.2 | D14: 64QAM 5/6 | E14: 144.4 | F14: ninguno | G14: 0
A15: 5 | B15: S2 | C15: 7 | D15: 64QAM 3/4 | E15: 130 | F15: QPSK 1/2 | G15: 28.9
A16: 6 | B16: S2 | C16: 8.9 | D16: 64QAM 3/4 | E16: 130 | F16: QPSK 1/2 | G16: 28.9
A17: 7 | B17: S2 | C17: 10.2 | D17: 64QAM 5/6 | E17: 144.4 | F17: QPSK 3/4 | G17: 43.3
A18: 8 | B18: S2 | C18: 12.6 | D18: 64QAM 5/6 | E18: 144.4 | F18: 16QAM 1/2 | G18: 57.8
A19: 9 | B19: S2 | C19: 12 | D19: 64QAM 5/6 | E19: 144.4 | F19: 16QAM 1/2 | G19: 57.8
A20: 10 | B20: S2 | C20: 13.3 | D20: 64QAM 5/6 | E20: 144.4 | F20: 16QAM 1/2 | G20: 57.8
A21: 11 | B21: S2 | C21: 13.7 | D21: 256QAM 3/4 | E21: 173.3 | F21: 16QAM 1/2 | G21: 57.8
A22: 12 | B22: S2 | C22: 14.4 | D22: 64QAM 5/6 | E22: 144.4 | F22: 16QAM 1/2 | G22: 57.8
... A119: 109 | B119: S1 | C119: 2.7 | D119: 256QAM 3/4 | E119: 173.3 | F119: ninguno | G119: 0

Sheet Sensibilidad
A1: Escenarios de sensibilidad
A2: Resultados de analisis_e3.py (se recalcula todo el modelo por escenario).
A4: Escenario | B4: Casas con enlace útil ↓ y ↑ | C4: Margen mín. ↓ (dB) | D4: Margen mín. ↑ (dB) | E4: Margen mediano ↓ (dB) | F4: Util. máx. DL | G4: Casas > 30 dB follaje
A5: Base: torre 30 m, copa 20 m | B5: 109 | C5: 16.4 | D5: 13.4 | E5: 45.1 | F5: 0.48 | G5: 4
A6: Torre 24 m | B6: 108 | C6: 11.3 | D6: 8.3 | E6: 43.9 | F6: 0.56 | G6: 11
A7: Torre 36 m | B7: 109 | C7: 20.1 | D7: 17.1 | E7: 43.9 | F7: 0.46 | G7: 2
A8: Copa 15 m | B8: 109 | C8: 25.5 | D8: 22.5 | E8: 48.6 | F8: 0.42 | G8: 1
A9: Copa 25 m | B9: 108 | C9: 8.7 | D9: 5.7 | E9: 40.7 | F9: 0.54 | G9: 16
A10: Copa 25 m + torre 24 m | B10: 106 | C10: 2.7 | D10: -0.3 | E10: 43.1 | F10: 0.62 | G10: 19
A11: Desvanecimiento extra 6 dB (lluvia fuerte/arboles mojados) | B11: 108 | C11: 10.4 | D11: 7.4 | E11: 39.1 | F11: 0.65 | G11: 4
A12: Error de montaje +2 grados inclinacion | B12: 109 | C12: 14.4 | D12: 11.4 | E12: 45.4 | F12: 0.51 | G12: 4
A13: Error de montaje +4 grados inclinacion | B13: 105 | C13: 6.6 | D13: 3.6 | E13: 45.1 | F13: 0.52 | G13: 4
A16: Criterio: un enlace es útil si hay un MCS con margen ≥ 10 dB; margen mínimo < 10 dB activa la contingencia D08 (mástil de 10 m / CPE de mayor ganancia / relevo).

Sheet Energia
A1: Energía solar de la torre (dimensionamiento breve)
A2: No es el foco del proyecto: dimensionamiento simple, costos aproximados. Todo con fórmulas.
A4: Carga en la torre | B4: Cantidad | C4: Potencia unit. (W) | D4: Potencia (W) | E4: Fuente / nota
A5: Starlink Performance Gen 3 | B5: 1 | C5: 100 | D5: =B5*C5 -> 100 | E5: F18/F21: 75–100 W; se usa el valor alto
A6: Rocket Prism 5AC Gen2 | B6: 3 | C6: 9.5 | D6: =B6*C6 -> 28.5 | E6: F24
A7: Router + switch gigabit | B7: 1 | C7: 15 | D7: =B7*C7 -> 15 | E7: Supuesto
A8: Pérdidas de conversión (inversor, PoE) | D8: 0.1 | E8: Supuesto 10 %
A9: Potencia continua total (W) | D9: =SUM(D5:D7)*(1+D8) -> 157.85
A10: Energía diaria (kWh/día) | D10: =D9*24/1000 -> 3.7884
A11: Autonomía requerida sin sol (días) | D11: 2 | E11: Decisión: 2 días (meta de disponibilidad ≥ 99 %)
A12: Profundidad de descarga permitida (LiFePO4) | D12: 0.9 | E12: Supuesto típico LiFePO4
A13: Capacidad requerida (kWh) | D13: =D10*D11/D12 -> 8.4186667
A14: Capacidad por batería 48 V / 100 Ah (kWh) | D14: 5.12 | E14: F29: Relion RB48V100 (5.12 kWh)
A15: Baterías necesarias (unidades) | D15: =ROUNDUP(D13/D14,0) -> 2
A16: Horas solar pico, mes más desfavorable (kWh/m²/día) | D16: 3.5 | E16: SUPUESTO típico de la zona; verificar en NASA POWER (opcional)
A17: Rendimiento global del sistema FV (PR) | D17: 0.75 | E17: Supuesto típico
A18: Potencia FV requerida (kW) | D18: =D10/(D16*D17) -> 1.4432
A19: Potencia por panel (W) | D19: 550 | E19: Panel monocristalino de 550 W (formato estándar, F30)
A20: Paneles necesarios (unidades) | D20: =ROUNDUP(D18*1000/D19,0) -> 3
A21: Autonomía real con las baterías instaladas (días) | D21: =D15*D14*D12/D10 -> 2.4326893

Sheet BOM_CAPEX
A1: Lista de materiales y CAPEX (Q)
A2: Cantidades y precios en azul. Estado: "Fuente" = precio publicado (ver hoja Fuentes); "Estimación" = precio aproximado del autor, por cotizar.
A4: Ítem | B4: Categoría | C4: Cant. diseño | D4: Cant. año 1 | E4: Precio unit. | F4: Moneda | G4: Precio unit. (Q) | H4: Total diseño (Q) | I4: Total año 1 (Q) | J4: Estado / fuente
A5: Starlink Performance (Gen 3), plato | B5: Backhaul | C5: 1 | D5: 1 | E5: 1499 | F5: USD | G5: =IF(F5="USD",E5*Supuestos!$C$32,E5) -> 11459.105 | H5: =C5*G5 -> 11459.105 | I5: =D5*G5 -> 11459.105 | J5: Fuente F19/F20 (precio de planificación; rebaja a US$999)
A6: Adaptador de tubo Starlink | B6: Backhaul | C6: 1 | D6: 1 | E6: 480 | F6: GTQ | G6: =IF(F6="USD",E6*Supuestos!$C$32,E6) -> 480 | H6: =C6*G6 -> 480 | I6: =D6*G6 -> 480 | J6: Fuente F23 (tienda GT)
A7: Cable Starlink Performance 50 m | B7: Backhaul | C7: 1 | D7: 1 | E7: 1300 | F7: GTQ | G7: =IF(F7="USD",E7*Supuestos!$C$32,E7) -> 1300 | H7: =C7*G7 -> 1300 | I7: =D7*G7 -> 1300 | J7: Fuente F23 (tienda GT)
A8: Radio Rocket Prism 5AC Gen2 | B8: Radio | C8: 3 | D8: 3 | E8: 307.78 | F8: USD | G8: =IF(F8="USD",E8*Supuestos!$C$32,E8) -> 2352.8242 | H8: =C8*G8 -> 7058.4726 | I8: =D8*G8 -> 7058.4726 | J8: Fuente F24
A9: Antena sectorial AM-5G16-120 | B9: Radio | C9: 3 | D9: 3 | E9: 79 | F9: USD | G9: =IF(F9="USD",E9*Supuestos!$C$32,E9) -> 603.9155 | H9: =C9*G9 -> 1811.7465 | I9: =D9*G9 -> 1811.7465 | J9: Fuente F25
A10: Router PoE + switch central | B10: Red | C10: 1 | D10: 1 | E10: 250 | F10: USD | G10: =IF(F10="USD",E10*Supuestos!$C$32,E10) -> 1911.125 | H10: =C10*G10 -> 1911.125 | I10: =D10*G10 -> 1911.125 | J10: Estimación
A11: Inyectores PoE 24 V para radios | B11: Red | C11: 3 | D11: 3 | E11: 25 | F11: USD | G11: =IF(F11="USD",E11*Supuestos!$C$32,E11) -> 191.1125 | H11: =C11*G11 -> 573.3375 | I11: =D11*G11 -> 573.3375 | J11: Estimación
A12: CPE LiteBeam 5AC Gen2 | B12: Abonado | C12: 109 | D12: 65 | E12: 64.83 | F12: USD | G12: =IF(F12="USD",E12*Supuestos!$C$32,E12) -> 495.59294 | H12: =C12*G12 -> 54019.63 | I12: =D12*G12 -> 32213.541 | J12: Fuente F27
A13: Mástil galvanizado 6 m para CPE | B13: Abonado | C13: 109 | D13: 65 | E13: 25 | F13: USD | G13: =IF(F13="USD",E13*Supuestos!$C$32,E13) -> 191.1125 | H13: =C13*G13 -> 20831.263 | I13: =D13*G13 -> 12422.312 | J13: Estimación
A14: Cable UTP exterior 15 m + conectores | B14: Abonado | C14: 109 | D14: 65 | E14: 12 | F14: USD | G14: =IF(F14="USD",E14*Supuestos!$C$32,E14) -> 91.734 | H14: =C14*G14 -> 9999.006 | I14: =D14*G14 -> 5962.71 | J14: Estimación
A15: Router Wi-Fi interior | B15: Abonado | C15: 109 | D15: 65 | E15: 30 | F15: USD | G15: =IF(F15="USD",E15*Supuestos!$C$32,E15) -> 229.335 | H15: =C15*G15 -> 24997.515 | I15: =D15*G15 -> 14906.775 | J15: Estimación
A16: Punto de acceso comunitario exterior | B16: Comunidad | C16: 2 | D16: 2 | E16: 179 | F16: USD | G16: =IF(F16="USD",E16*Supuestos!$C$32,E16) -> 1368.3655 | H16: =C16*G16 -> 2736.731 | I16: =D16*G16 -> 2736.731 | J16: Estimación
... A19: Cable UTP blindado y accesorios de torre | B19: Torre | C19: 1 | D19: 1 | E19: 250 | F19: USD | G19: =IF(F19="USD",E19*Supuestos!$C$32,E19) -> 1911.125 | H19: =C19*G19 -> 1911.125 | I19: =D19*G19 -> 1911.125 | J19: Estimación
A20: Panel solar 550 W | B20: Energía | C20: =Energia!$D$20 -> 3 | D20: =Energia!$D$20 -> 3 | E20: 165 | F20: USD | G20: =IF(F20="USD",E20*Supuestos!$C$32,E20) -> 1261.3425 | H20: =C20*G20 -> 3784.0275 | I20: =D20*G20 -> 3784.0275 | J20: Estimación
A21: Batería LiFePO4 48 V 100 Ah (5.12 kWh) | B21: Energía | C21: =Energia!$D$15 -> 2 | D21: =Energia!$D$15 -> 2 | E21: 3495.95 | F21: USD | G21: =IF(F21="USD",E21*Supuestos!$C$32,E21) -> 26724.79 | H21: =C21*G21 -> 53449.58 | I21: =D21*G21 -> 53449.58 | J21: Fuente F29
A22: Controlador MPPT + inversor 1 kW | B22: Energía | C22: 1 | D22: 1 | E22: 950 | F22: USD | G22: =IF(F22="USD",E22*Supuestos!$C$32,E22) -> 7262.275 | H22: =C22*G22 -> 7262.275 | I22: =D22*G22 -> 7262.275 | J22: Estimación
A23: Estructura de paneles, protecciones y gabinete | B23: Energía | C23: 1 | D23: 1 | E23: 1300 | F23: USD | G23: =IF(F23="USD",E23*Supuestos!$C$32,E23) -> 9937.85 | H23: =C23*G23 -> 9937.85 | I23: =D23*G23 -> 9937.85 | J23: Estimación
A24: Instalación de torre y radios (cuadrilla) | B24: Servicios | C24: 1 | D24: 1 | E24: 3000 | F24: USD | G24: =IF(F24="USD",E24*Supuestos!$C$32,E24) -> 22933.5 | H24: =C24*G24 -> 22933.5 | I24: =D24*G24 -> 22933.5 | J24: Estimación
A25: Instalación de CPE en casas (mano de obra) | B25: Servicios | C25: 109 | D25: 65 | E25: 20 | F25: USD | G25: =IF(F25="USD",E25*Supuestos!$C$32,E25) -> 152.89 | H25: =C25*G25 -> 16665.01 | I25: =D25*G25 -> 9937.85 | J25: Estimación
A26: Transporte y viáticos | B26: Servicios | C26: 1 | D26: 1 | E26: 1500 | F26: USD | G26: =IF(F26="USD",E26*Supuestos!$C$32,E26) -> 11466.75 | H26: =C26*G26 -> 11466.75 | I26: =D26*G26 -> 11466.75 | J26: Estimación
A28: Flete, aduana y gastos de importación (% de equipos) | G28: 0.1 | J28: Supuesto; IVA 12 % se considera acreditable (empresa legalizada)
A29: Imprevistos (%) | G29: 0.1 | J29: Supuesto
A30: Subtotal ítems | H30: =SUM(H5:H26) -> 328037.4 | I30: =SUM(I5:I26) -> 276968.16
A31: Flete y aduana | H31: =H30*$G$28 -> 32803.74 | I31: =I30*$G$28 -> 27696.816
A32: Imprevistos | H32: =(H30+H31)*$G$29 -> 36084.114 | I32: =(I30+I31)*$G$29 -> 30466.498
A33: CAPEX TOTAL (Q) | H33: =SUM(H30:H32) -> 396925.25 | I33: =SUM(I30:I32) -> 335131.48
A34: CAPEX TOTAL (US$) | H34: =H33/Supuestos!$C$32 -> 51922.984 | I34: =I33/Supuestos!$C$32 -> 43839.555
A35: Hogares con servicio (puntos CPE) | H35: 98 | I35: 65
A36: CAPEX por hogar (Q) | H36: =H33/H35 -> 4050.2577 | I36: =I33/I35 -> 5155.8689
A37: Nota: la columna "diseño" equipa 109 puntos (máximo), pero el CAPEX por hogar divide entre los 98 puntos de adopción del año 3.

Sheet OPEX_Tarifa
A1: OPEX mensual, costo por hogar y tarifa de equilibrio (Q)
A2: Plan Starlink: Prioridad Local 2 TB Q2,970/mes + bloques de 50 GB a Q140 (F08).
A4: Concepto | B4: Año 1 | C4: Año 3 | D4: Nota
A5: Puntos con servicio (CPE + 2 hotspots) | B5: 67 | C5: 100 | D5: Año 1: 65 + 2; año 3: 98 + 2
A6: Consumo mensual por punto (GB) | B6: 25 | C6: 25 | D6: Supuesto
A7: Consumo total (GB/mes) | B7: =B5*B6 -> 1675 | C7: =C5*C6 -> 2500
A8: Bloques extra de 50 GB | B8: =ROUNDUP(MAX(0,B7-2000)/50,0) -> 0 | C8: =ROUNDUP(MAX(0,C7-2000)/50,0) -> 10
A9: Plan Starlink 2 TB (Q/mes) | B9: 2970 | C9: 2970 | D9: F08
A10: Bloque extra de 50 GB (Q) | B10: 140 | C10: 140 | D10: F08
A11: Suscripción Starlink (Q/mes) | B11: =B9+B8*B10 -> 2970 | C11: =C9+C8*C10 -> 4370
A12: Mantenimiento (2 % anual del CAPEX) | B12: =0.02*BOM_CAPEX!$I$33/12 -> 558.55246 | C12: =0.02*BOM_CAPEX!$H$33/12 -> 661.54209 | D12: Supuesto
A13: Técnico local (medio tiempo) | B13: 2000 | C13: 2000 | D13: Supuesto
A14: Reserva de reposición de CPE (5 % anual) | B14: =0.05*BOM_CAPEX!I12/12 -> 134.22309 | C14: =0.05*BOM_CAPEX!H12/12 -> 225.08179 | D14: Supuesto
A15: Reserva de reposición de baterías (vida 10 años) | B15: =BOM_CAPEX!I21/120 -> 445.41316 | C15: =BOM_CAPEX!H21/120 -> 445.41316 | D15: LiFePO4 ≈ 6,000 ciclos (supuesto)
A16: Seguro (1 % anual del CAPEX) | B16: =0.01*BOM_CAPEX!$I$33/12 -> 279.27623 | C16: =0.01*BOM_CAPEX!$H$33/12 -> 330.77104 | D16: Supuesto
A17: Administración, cobranza y soporte | B17: 500 | C17: 500 | D17: Supuesto
A18: OPEX MENSUAL TOTAL (Q) | B18: =SUM(B11:B17) -> 6887.4649 | C18: =SUM(C11:C17) -> 8532.8081
A19: Hogares con servicio | B19: 65 | C19: 98
A20: OPEX por hogar por mes (Q) | B20: =B18/B19 -> 105.961 | C20: =C18/C19 -> 87.06947
A21: Amortización del CAPEX a 5 años por hogar y mes (Q) | B21: =BOM_CAPEX!$I$36/60 -> 85.931148 | C21: =BOM_CAPEX!$H$36/60 -> 67.504295
A22: TARIFA DE EQUILIBRIO por hogar y mes (Q) | B22: =B20+B21 -> 191.89215 | C22: =C20+C21 -> 154.57376 | D22: OPEX + CAPEX amortizado, sin margen de utilidad
A23: Tarifa propuesta (Q/mes) | C23: 175 | D23: Decisión comercial (compárese con planes móviles rurales)
A24: Ingreso mensual año 3 (Q) | C24: =C23*C19 -> 17150
A25: Margen mensual año 3 tras OPEX (Q) | C25: =C24-C18 -> 8617.1919
A26: Recuperación simple del CAPEX (meses) | C26: =IF(C25>0,BOM_CAPEX!$H$33/C25,"no se recupera") -> 46.062018 | D26: Con 98 hogares pagando la tarifa propuesta

Sheet Legal
A1: Marco legal y regulatorio (Guatemala)
A2: Se asume que somos parte de una empresa operadora ya legalizada. Las citas marcadas "por verificar" deben contrastarse con el texto oficial.
A4: Tema | B4: Qué exige / dice | C4: Cómo lo cumple el proyecto
A5: Ley General de Telecomunicaciones (Decreto 94-96) | B5: Regula el uso del espectro y los servicios de telecomunicaciones; la SIT es el ente regulador (F05, por verificar en texto oficial). | C5: Se opera bajo una empresa con registro ante la SIT; el servicio se presta como acceso a internet de banda ancha.
A6: Tabla Nacional de Atribución de Frecuencias (TNAF) | B6: La SIT administra la TNAF (F06). Referencia regional: 5725–5850 MHz figura como banda 5 GHz usable en Guatemala; límites de potencia y certificación deben confirmarse en la TNAF vigente (F28, por verificar). | C6: Los tres canales (5745/5785/5825 MHz, 20 MHz) quedan dentro de 5725–5850 MHz; equipos con certificación FCC/CE; potencia total dentro del límite aplicable (por verificar).
A7: Registro de operador y servicio | B7: Los prestadores de servicios inscriben ante el Registro de Telecomunicaciones (ORC) (F04). | C7: La empresa operadora inscribe el servicio y la aldea como zona de cobertura.
A8: Starlink | B8: La SIT autorizó Starlink en mayo de 2023 (F02); el servicio es comercial con planes Business en Guatemala (F08). | C8: El backhaul se contrata como cliente Business (Prioridad Local); no se revende sin registro del servicio.
A9: Uso del terreno de la torre | B9: Se requiere autorización del propietario o de la comunidad (usufructo/servidumbre) y permisos municipales. | C9: Acuerdo con la COCODE/alcalde auxiliar para el claro central; obra civil con permiso municipal de Chisec.
A10: Seguridad de la torre | B10: Cimentación, vientos y pararrayos calculados por un profesional; señalización si aplica (aviación civil, por verificar). | C10: Torre ventada de 30 m con pararrayos y puesta a tierra incluidos en el CAPEX.
A11: Sanciones | B11: La LGT prevé multas por operar sin título o fuera de la banda (art. 81, F05, por verificar). | C11: Operación solo en banda atribuida y con registro; plan de frecuencias documentado en esta memoria.

Sheet Fuentes
A1: Fuentes y trazabilidad
A2: Copia de 14_fuentes/FUENTES.md (se actualizó con F28–F30).
A4: ID | B4: Dato usado | C4: Fuente | D4: Consulta | E4: Estado
A5: F01 | B5: Planes Starlink GT: Lite Q365, Max Q545, Roam 100GB Q410, Roam Ilimitado Q820 | C5: https://livinginguatemala.com/digital-nomad/starlink-in-guatemala/ | D5: 22-oct-2026 | E5: Secundaria; confirmar en starlink.com/gt
A6: F02 | B6: Lanzamiento 14-jul-2023; SIT autorizó 19-may-2023 | C6: https://www.revistaeyn.com/tecnologia-cultura-digital/starlink-llega-a-guatemala-con-precios-especiales-DC14436342 | D6: 22-oct-2026 | E6: Prensa
A7: F03 | B7: Alza de precios Starlink 2026 (EE. UU.) | C7: https://www.satelliteinternet.com/resources/starlink-2026-price-increase/ | D7: 22-oct-2026 | E7: Solo contexto
A8: F04 | B8: Requisitos servicios satelitales (licencia, usuario de facilidades, registro ORC) | C8: https://www.bloomberglinea.com/2022/11/16/starlink-de-elon-musk-en-guatemala-que-necesita-para-que-pueda-operar/ | D8: 22-oct-2026 | E8: Artículo 2022; verificar en SIT
A9: F05 | B9: Decreto 94-96, Acuerdo Gubernativo 574-98, art. 81 sanciones | C9: https://livinginguatemala.com/guides/satellite-messengers-guatemala | D9: 22-oct-2026 | E9: Secundaria; verificar texto oficial
A10: F06 | B10: TNAF administrada por SIT | C10: https://dplnews.com/?p=270771 | D10: 22-oct-2026 | E10: Prensa
A11: F07 | B11: Censo 2018: 29 % usa Internet (7+ años); brechas departamentales | C11: https://dplnews.com/censo-refleja-brechas-en-el-uso-de-internet/ | D11: 22-oct-2026 | E11: Prensa
A12: F08 | B12: Starlink Business GT, Prioridad Local: 50 GB Q310, 500 GB Q870, 1 TB Q1,570, 2 TB Q2,970; +50 GB Q140. Prioridad Global: 50 GB Q1,920, 500 GB Q5,000, 1 TB Q8,850, 2 TB Q16,550 | C12: Captura propia starlink.com, 23-oct-2026 (`evidencias/starlink_business_planes_prioridad.png`) | D12: 23-oct-2026 | E12: Primaria
A13: F09 | B13: Disponibilidad "Disponible ahora"; descarga 145–276 Mbps en 15.88908, -90.53177 | C13: Capturas propias starlink.com (`evidencias/starlink_*_babilonia.png`) | D13: 23-oct-2026 | E13: Primaria
A14: F10 | B14: Ubicación y entorno de Babilonia, Chisec | C14: Capturas Google Maps (`evidencias/maps_*`) | D14: 23-oct-2026 | E14: Primaria
A15: F11 | B15: Starlink en la zona: subida 21–39 Mbps, latencia 22–32 ms | C15: Capturas propias starlink.com (`evidencias/starlink_subida_*`, `starlink_latencia_*`) | D15: 25-oct-2026 | E15: Primaria
... A34: F30 | B34: Panel solar 550 W, 144 celdas monocristalino (formato estándar); precio US$165 es estimación | C34: https://a1solarstore.com/solar-panels/550-watt-solar-panels.html?page_id=93 | D34: 27-oct-2026 | E34: Solo formato; precio estimado
